testcontainers/k3s/__init__.py
tests/test_k3s.py
testcontainers_k3s-0.0.1rc1.dist-info/METADATA
testcontainers_k3s-0.0.1rc1.dist-info/WHEEL
testcontainers_k3s-0.0.1rc1.dist-info/top_level.txt
testcontainers_k3s-0.0.1rc1.dist-info/RECORD
